{
    "fallback": "minecraft:empty",
    "elements": [
      {
        "weight": 1,
        "element": {
          "element_type": "minecraft:single_pool_element",
          "projection": "rigid",
          "location": "bro:tower/loot_big1",
          "override_liquid_settings": "ignore_waterlogging",
          "processors": "minecraft:empty"
        }
      },
      {
        "weight": 1,
        "element": {
          "element_type": "minecraft:single_pool_element",
          "projection": "rigid",
          "location": "bro:tower/loot_big2",
          "override_liquid_settings": "ignore_waterlogging",
          "processors": "minecraft:empty"
        }
      },
      {
        "weight": 1,
        "element": {
          "element_type": "minecraft:single_pool_element",
          "projection": "rigid",
          "location": "bro:tower/loot_big3",
          "override_liquid_settings": "ignore_waterlogging",
          "processors": "minecraft:empty"
        }
      },
      {
        "weight": 1,
        "element": {
          "element_type": "minecraft:single_pool_element",
          "projection": "rigid",
          "location": "bro:tower/loot_big4",
          "override_liquid_settings": "ignore_waterlogging",
          "processors": "minecraft:empty"
        }
      },
      {
        "weight": 1,
        "element": {
          "element_type": "minecraft:single_pool_element",
          "projection": "rigid",
          "location": "bro:tower/loot_big5",
          "override_liquid_settings": "ignore_waterlogging",
          "processors": "minecraft:empty"
        }
      },
      {
        "weight": 1,
        "element": {
          "element_type": "minecraft:single_pool_element",
          "projection": "rigid",
          "location": "bro:tower/loot_big6",
          "override_liquid_settings": "ignore_waterlogging",
          "processors": "minecraft:empty"
        }
      },
      {
        "weight": 1,
        "element": {
          "element_type": "minecraft:single_pool_element",
          "projection": "rigid",
          "location": "bro:tower/loot_big7",
          "override_liquid_settings": "ignore_waterlogging",
          "processors": "minecraft:empty"
        }
      },
      {
        "weight": 1,
        "element": {
          "element_type": "minecraft:single_pool_element",
          "projection": "rigid",
          "location": "bro:tower/loot_big8",
          "override_liquid_settings": "ignore_waterlogging",
          "processors": "minecraft:empty"
        }
      }
    ]
  }
  